LICENSE.md
setdiff/__init__.py
setdiff/sett.py
setdiff-1.0.2.dist-info/entry_points.txt
setdiff-1.0.2.dist-info/LICENSE.md
setdiff-1.0.2.dist-info/WHEEL
setdiff-1.0.2.dist-info/METADATA
setdiff-1.0.2.dist-info/RECORD
